topsis_neeraj_102003710/__init__.py
topsis_neeraj_102003710/topsis_neeraj_102003710.py
topsis_neeraj_102003710-0.0.2.dist-info/LICENSE
topsis_neeraj_102003710-0.0.2.dist-info/METADATA
topsis_neeraj_102003710-0.0.2.dist-info/WHEEL
topsis_neeraj_102003710-0.0.2.dist-info/top_level.txt
topsis_neeraj_102003710-0.0.2.dist-info/RECORD
